cloudprovider/__init__.py
cloudprovider/aws.py
cloudprovider/azure.py
tests/__init__.py
tests/test_aws.py
cloudprovider-1.0.3.dist-info/METADATA
cloudprovider-1.0.3.dist-info/WHEEL
cloudprovider-1.0.3.dist-info/top_level.txt
cloudprovider-1.0.3.dist-info/RECORD
