Metadata-Version: 2.1
Name: cloudprovider
Version: 1.0.3
Summary: Multi cloud provider
Author: Maha Arunachalam
License: MIT
Requires-Dist: boto3
Requires-Dist: azure-identity
Requires-Dist: azure-mgmt-compute
